PetriNet2Vec.py
__init__.py
PetriNet2Vec-1.0.3.post1.dist-info/LICENSE
PetriNet2Vec-1.0.3.post1.dist-info/METADATA
PetriNet2Vec-1.0.3.post1.dist-info/WHEEL
PetriNet2Vec-1.0.3.post1.dist-info/top_level.txt
PetriNet2Vec-1.0.3.post1.dist-info/RECORD
