Metadata-Version: 2.1
Name: PetriNet2Vec
Version: 1.0.3.post1
Summary: Process Mining Embeddings: Learning Representations for Petri Nets
Author-email: "Juan G. Colonna" <juancolonna@icomp.edu.ufam.br>
License: Copyright (c) 2024 Juan Gabriel Colonna
Classifier: Programming Language :: Python :: 3
Classifier: License :: OSI Approved :: MIT License
Classifier: Operating System :: OS Independent
Requires-Python: >=3.10.12
License-File: LICENSE
Requires-Dist: numpy
Requires-Dist: pm4py
Requires-Dist: gensim
Requires-Dist: scipy ==1.11.1
